LICENSE.txt
MANIFEST.in
README.md
setup.py
./langdash/__init__.py
./langdash/infer.py
./langdash/llm.py
./langdash/llm_session.py
./langdash/response.py
./langdash/sampling.py
./langdash/classify/__init__.py
./langdash/classify/token_qa.py
./langdash/models/__init__.py
./langdash/models/sentence_transformers.py
./langdash/models/transformers.py
./langdash/search/__init__.py
./langdash/search/embedding_search.py
./langdash/search/engine.py
./langdash/search/multichoice_search.py
langdash/__init__.py
langdash/core.py
langdash/infer.py
langdash/llm.py
langdash/llm_config.py
langdash/llm_session.py
langdash/logit_preprocessors.py
langdash/response.py
langdash/sampling.py
langdash.egg-info/PKG-INFO
langdash.egg-info/SOURCES.txt
langdash.egg-info/dependency_links.txt
langdash.egg-info/requires.txt
langdash.egg-info/top_level.txt
langdash/chains/__init__.py
langdash/chains/chains.py
langdash/chains/nodes.py
langdash/chains/typing.py
langdash/chat/__init__.py
langdash/chat/chat.py
langdash/classify/__init__.py
langdash/classify/token_qa.py
langdash/extern/rwkv-cpp-ggml-max-nodes.patch
langdash/models/__init__.py
langdash/models/ctransformers.py
langdash/models/llama_cpp.py
langdash/models/rwkv_cpp.py
langdash/models/sentence_transformers.py
langdash/models/transformers.py
langdash/models/_mixins/__init__.py
langdash/models/_mixins/tensor_based_infer_mixin.py
langdash/models/_tokenizer/__init__.py
langdash/models/_tokenizer/_bpe.py
langdash/models/_tokenizer/bytes_dict_tokenizer.py
langdash/models/_tokenizer/hf_tokenizer.py
langdash/models/_tokenizer/rwkv_tokenizer.py
langdash/models/_tokenizer/tokenizer.py
langdash/search/__init__.py
langdash/search/embedding_search.py
langdash/search/engine.py
langdash/search/multichoice_search.py