Metadata-Version: 2.1
Name: langdash
Version: 1.16.0
Summary: A simple library for interfacing with language models.
Home-page: https://git.mysymphony.jp.net/nana/langdash
Author: Nana Mochizuki
Author-email: nana@mysymphony.jp.net
Project-URL: Source, https://git.mysymphony.jp.net/nana/langdash
Project-URL: Documentation, https://langdash.readthedocs.io/en/latest/
Classifier: Development Status :: 4 - Beta
Classifier: Intended Audience :: Developers
Classifier: Topic :: Software Development :: Libraries
Classifier: License :: OSI Approved :: Apache Software License
Classifier: Programming Language :: Python :: 3
Classifier: Programming Language :: Python :: 3.8
Requires-Python: >=3.8
Provides-Extra: embeddings
Provides-Extra: rwkv_cpp
Provides-Extra: llama_cpp
Provides-Extra: transformers
Provides-Extra: ctransformers
Provides-Extra: sentence_transformers
License-File: LICENSE.txt
